AUTHORS.txt
CHANGES.txt
HGREV
LICENSE.txt
MANIFEST.in
README.txt
TODO.txt
setup.py
django_errorstack.egg-info/PKG-INFO
django_errorstack.egg-info/SOURCES.txt
django_errorstack.egg-info/dependency_links.txt
django_errorstack.egg-info/not-zip-safe
django_errorstack.egg-info/top_level.txt
errorstack/__init__.py
errorstack/handlers.py
errorstack/middleware.py
errorstack/models.py
errorstack/settings.py
errorstack/tests/__init__.py
errorstack/tests/runtests.py
errorstack/tests/tests.py