Metadata-Version: 1.0
Name: django-errorstack
Version: 0.1.0
Summary: Easy Django integration with the ErrorStack.com service
Home-page: http://bitbucket.org/carljm/django-errorstack/
Author: Carl Meyer
Author-email: carl@dirtcircle.com
License: UNKNOWN
Platform: UNKNOWN
Classifier: Development Status :: 3 - Alpha
Classifier: Environment :: Web Environment
Classifier: Intended Audience :: Developers
Classifier: License :: OSI Approved :: BSD License
Classifier: Operating System :: OS Independent
Classifier: Programming Language :: Python
Classifier: Framework :: Django
